{"type":"Box","props":{"y":0,"x":0,"width":200,"presetID":1,"name":"FoodTrigger","isPresetRoot":true,"height":80},"compId":35,"child":[{"type":"Script","props":{"presetID":2,"runtime":"source/FoodTrigger.js"},"compId":39},{"type":"Sprite","props":{"y":-17,"x":39,"texture":"source/landscape/cao5.png","presetID":3},"compId":63},{"type":"Sprite","props":{"y":35.5,"x":135,"texture":"source/landscape/cao5.png","presetID":4},"compId":64},{"type":"Sprite","props":{"y":-21.5,"x":143,"texture":"source/landscape/cao5.png","presetID":6},"compId":66},{"type":"Sprite","props":{"y":35.5,"x":39,"texture":"source/landscape/cao5.png","presetID":5},"compId":65},{"type":"Sprite","props":{"y":-21.5,"x":-57,"texture":"source/landscape/cao5.png","presetID":7},"compId":67},{"type":"Sprite","props":{"y":35.5,"x":-28.5,"texture":"source/landscape/cao5.png","presetID":8},"compId":68},{"type":"Sprite","props":{"y":7,"x":81.5,"texture":"source/landscape/cao5.png","presetID":9},"compId":69},{"type":"Sprite","props":{"y":-43,"x":81.5,"texture":"source/landscape/cao5.png","presetID":10},"compId":70},{"type":"Sprite","props":{"y":0,"x":-3.5,"texture":"source/landscape/cao5.png","presetID":11},"compId":71},{"type":"Sprite","props":{"y":14,"x":185.5,"texture":"source/landscape/cao5.png","presetID":12},"compId":72}],"loadList":["source/landscape/cao5.png"],"loadList3D":[]}