{"type":"Dialog","props":{"width":1336,"height":750,"autoDestroyAtClosed":true},"compId":2,"child":[{"type":"Box","props":{"y":-4260,"x":-4280,"width":10000,"name":"under","height":10000,"bgColor":"#000000","alpha":0.5},"compId":17},{"type":"Image","props":{"y":275,"x":518,"width":800,"skin":"source/ui/panelUnder.png","pivotY":150,"pivotX":250,"height":500,"sizeGrid":"92,110,76,112"},"compId":4},{"type":"Button","props":{"y":181,"x":1010,"width":27,"stateNum":1,"skin":"source/ui/close.png","scaleY":1.5,"scaleX":1.5,"pivotY":14,"pivotX":14,"name":"closeBtn","height":27},"compId":5},{"type":"Script","props":{"runtime":"scene/ShopDialogLogic.js"},"compId":6},{"type":"Button","props":{"y":382,"x":621,"width":66,"stateNum":1,"skin":"source/ui/btn4.png","rotation":90,"pivotY":34,"pivotX":33,"name":"leftBtn","height":67},"compId":9},{"type":"Button","props":{"y":382,"x":375,"width":66,"stateNum":1,"skin":"source/ui/btn4.png","rotation":270,"pivotY":34,"pivotX":33,"name":"rightBtn","height":67},"compId":10},{"type":"Button","props":{"y":528,"x":499,"width":274,"stateNum":1,"skin":"source/ui/btn7.png","scaleY":0.7,"scaleX":0.7,"name":"yesBtn","height":120,"anchorY":0.5,"anchorX":0.5},"compId":15},{"type":"Image","props":{"y":384,"x":494,"width":100,"skin":"comp/image.png","name":"icon","height":100,"anchorY":0.5,"anchorX":0.5},"compId":16},{"type":"Text","props":{"y":256,"x":499,"width":200,"valign":"middle","text":"text","pivotY":24,"pivotX":100,"name":"nameText","height":48,"fontSize":48,"font":"Microsoft YaHei","color":"#f674ae","bold":true,"align":"center","runtime":"Laya.Text"},"compId":18},{"type":"Animation","props":{"y":449,"x":863,"source":"anim/Man.ani","scaleY":2,"scaleX":2,"autoPlay":true,"autoAnimation":"idle"},"compId":36}],"loadList":["source/ui/panelUnder.png","source/ui/close.png","source/ui/btn4.png","source/ui/btn7.png","comp/image.png","anim/Man.ani"],"loadList3D":[]}